LICENSE
README.rst
setup.py
npccp/__init__.py
npccp/lib.py
npccp.egg-info/PKG-INFO
npccp.egg-info/SOURCES.txt
npccp.egg-info/dependency_links.txt
npccp.egg-info/requires.txt
npccp.egg-info/top_level.txt
npccp/pcd/PcdReader.py
npccp/pcd/PcdWriter.py
npccp/pcd/__init__.py
npccp/pcd/header/PcdHeader.py
npccp/pcd/header/PcdXyzRgbHeader.py
npccp/pcd/header/PcdXyziHeader.py
npccp/pcd/header/__init__.py
npccp/pcd/utils/PcdUtils.py
npccp/pcd/utils/__init__.py
npccp/potree/HBatch.py
npccp/potree/HChunk.py
npccp/potree/HNode.py
npccp/potree/Node.py
npccp/potree/Point.py
npccp/potree/PotreeWriter.py
npccp/potree/__init__.py
npccp/potree/attribute/Attribute.py
npccp/potree/attribute/IndexAttribute.py
npccp/potree/attribute/IntensityAttribute.py
npccp/potree/attribute/PositionAttribute.py
npccp/potree/attribute/RgbAttribute.py
npccp/potree/attribute/__init__.py
npccp/potree/sampler/PotreeIndexerSampler.py
npccp/potree/sampler/PotreeIndexerSamplerStep.py
npccp/potree/sampler/__init__.py
npccp/potree/utils/PotreeChunksUtils.py
npccp/potree/utils/PotreeUtils.py
npccp/potree/utils/__init__.py
npccp/utils/ByteUtils.py
npccp/utils/RandomStringUtils.py
npccp/utils/__init__.py